calc/__init__.py
calc/simples.py
teste_pypip-0.16.0.dist-info/LICENSE.txt
teste_pypip-0.16.0.dist-info/METADATA
teste_pypip-0.16.0.dist-info/WHEEL
teste_pypip-0.16.0.dist-info/top_level.txt
teste_pypip-0.16.0.dist-info/RECORD
