Metadata-Version: 2.1
Name: teste-pypip
Version: 0.16.0
Summary: teste de pacote python
Home-page: UNKNOWN
Author: Thiago Rocha Ferreira
Author-email: thiagorocha503@gmail.com
License: MIT License
Keywords: teste_pypip
Platform: UNKNOWN
